<?xml version="1.0" encoding="UTF-8" standalone="yes"?>
<node artifactManager="be.nabu.eai.module.services.vm.VMServiceManager" created="2023-01-29T22:45:44.633+01:00" lastModified="2025-08-26T12:22:00.913+02:00" leaf="true" version="15">
    <environmentId>ares</environmentId>
    <hidden>false</hidden>
    <locked>false</locked>
    <properties/>
    <references>nabu.frameworks.process.crud.processActionInstance.types.outputForRollback</references>
    <references>nabu.frameworks.process.crud.processActionInstance.services.update</references>
    <references>nabu.utils.Server.getServerName</references>
    <references>nabu.frameworks.process.services.getSupportedConnections</references>
    <references>nabu.frameworks.process.crud.processInstanceLog.services.create</references>
    <references>java.util.Date</references>
    <references>nabu.utils.Date.now</references>
    <references>nabu.frameworks.process.providers.action.service.startup.failRunningActions</references>
    <references>nabu.frameworks.process.crud.processActionInstance.services.listForRollback</references>
    <references>java.lang.String</references>
</node>
